greyjack-0.3.8.dist-info/METADATA
greyjack-0.3.8.dist-info/WHEEL
greyjack-0.3.8.dist-info/licenses/LICENSE
greyjack/SolverOOP.py
greyjack/SolverPureMath.py
greyjack/__init__.py
greyjack/agents/GeneticAlgorithm.py
greyjack/agents/LSHADE.py
greyjack/agents/LateAcceptance.py
greyjack/agents/SimulatedAnnealing.py
greyjack/agents/TabuSearch.py
greyjack/agents/__init__.py
greyjack/agents/base/Agent.py
greyjack/agents/base/GJSolution.py
greyjack/agents/base/LoggingLevel.py
greyjack/agents/base/ParallelizationBackend.py
greyjack/agents/base/__init__.py
greyjack/agents/base/individuals/Individual.py
greyjack/agents/base/individuals/IndividualHardMediumSoft.py
greyjack/agents/base/individuals/IndividualHardSoft.py
greyjack/agents/base/individuals/IndividualSimple.py
greyjack/agents/base/individuals/__init__.py
greyjack/agents/metaheuristic_bases/GeneticAlgorithmBase.py
greyjack/agents/metaheuristic_bases/LSHADEBase.py
greyjack/agents/metaheuristic_bases/LateAcceptanceBase.py
greyjack/agents/metaheuristic_bases/SimulatedAnnealingBase.py
greyjack/agents/metaheuristic_bases/TabuSearchBase.py
greyjack/agents/metaheuristic_bases/__init__.py
greyjack/agents/termination_strategies/ScoreLimit.py
greyjack/agents/termination_strategies/ScoreNoImprovement.py
greyjack/agents/termination_strategies/StepsLimit.py
greyjack/agents/termination_strategies/TerminationStrategy.py
greyjack/agents/termination_strategies/TimeSpentLimit.py
greyjack/agents/termination_strategies/__init__.py
greyjack/cotwin/CotwinBase.py
greyjack/cotwin/__init__.py
greyjack/greyjack.cp313-win_amd64.pyd
greyjack/persistence/CotwinBuilderBase.py
greyjack/persistence/DomainBuilderBase.py
greyjack/persistence/__init__.py
greyjack/pure_math/Constraint.py
greyjack/pure_math/MathModel.py
greyjack/pure_math/Objective.py
greyjack/pure_math/__init__.py
greyjack/pure_math/variables/BinaryVar.py
greyjack/pure_math/variables/FloatVar.py
greyjack/pure_math/variables/IntegerVar.py
greyjack/pure_math/variables/__init__.py
greyjack/score_calculation/__init__.py
greyjack/score_calculation/greynet/__init__.py
greyjack-0.3.8.dist-info/RECORD
