Metadata-Version: 2.4
Name: greyjack
Version: 0.3.8
Classifier: Development Status :: 5 - Production/Stable
Classifier: Intended Audience :: Science/Research
Classifier: Intended Audience :: Developers
Classifier: License :: OSI Approved :: MIT License
Classifier: License :: OSI Approved :: Apache Software License
Classifier: Programming Language :: Python
Classifier: Programming Language :: Python :: 3
Classifier: Programming Language :: Python :: 3.9
Classifier: Programming Language :: Python :: 3.10
Classifier: Programming Language :: Python :: 3.11
Classifier: Programming Language :: Python :: 3.12
Classifier: Programming Language :: Python :: 3.13
Classifier: Programming Language :: Python :: 3 :: Only
Classifier: Programming Language :: Python :: Implementation :: CPython
Classifier: Topic :: Software Development
Classifier: Topic :: Scientific/Engineering
Classifier: Operating System :: OS Independent
Classifier: Operating System :: Microsoft :: Windows
Classifier: Operating System :: Unix
Classifier: Operating System :: MacOS
Requires-Dist: bitarray>=3.5.0
Requires-Dist: dill
Requires-Dist: maturin>=1.9.1
Requires-Dist: mmh3>=5.1.0
Requires-Dist: multiprocess
Requires-Dist: mypy
Requires-Dist: mypy-extensions
Requires-Dist: mypy-protobuf
Requires-Dist: numba>=0.60.0
Requires-Dist: numpy
Requires-Dist: pathos
Requires-Dist: polars
Requires-Dist: pyarrow
Requires-Dist: pyzmq
License-File: LICENSE
Summary: GreyJack Solver is a constraint metaheuristic solver for Python, built on the robust foundations of Rust and Polars. It empowers you to tackle a wide array of constraint optimization problems, including continuous, integer, and mixed-integer challenges with ease and efficiency.
Keywords: greyjack,solver,optimization,polars,metaheuristic,genetic algorithm
Author-email: "Egor Chnegov (CameleoGrey)" <cameleogrey@yandex.ru>
Maintainer-email: "Egor Chnegov (CameleoGrey)" <cameleogrey@yandex.ru>
Requires-Python: >=3.9
Project-URL: Homepage, https://github.com/CameleoGrey/greyjack-solver-python
Project-URL: Documentation, https://github.com/CameleoGrey/greyjack-solver-python
Project-URL: Repository, https://github.com/CameleoGrey/greyjack-solver-python.git
Project-URL: Issues, https://github.com/CameleoGrey/greyjack-solver-python/issues
